boltun/__about__.py
boltun/__init__.py
boltun/__main__.py
boltun/__version__.py
boltun/contrib/__init__.py
boltun/engine/__init__.py
boltun/engine/_base.py
boltun/engine/environment/__init__.py
boltun/engine/environment/_base.py
boltun/engine/environment/extension/__init__.py
boltun/engine/environment/extension/_base.py
boltun/engine/environment/extension/core/__init__.py
boltun/engine/environment/extension/debug/__init__.py
boltun/engine/environment/extension/nlp/__init__.py
boltun/engine/environment/extension/nlp/namespaces/__init__.py
boltun/engine/environment/extension/nlp/namespaces/alias.py
boltun/engine/environment/extension/nlp/namespaces/intent.py
boltun/engine/environment/extension/nlp/namespaces/slot.py
boltun/engine/environment/mapping/__init__.py
boltun/engine/environment/mapping/_base.py
boltun/engine/environment/mapping/definition/__init__.py
boltun/engine/environment/mapping/definition/_base.py
boltun/engine/environment/mapping/definition/resolvers.py
boltun/engine/grammar/__init__.py
boltun/engine/grammar/exceptions.py
boltun/engine/grammar/nodes.py
boltun/engine/grammar/antlr4/Antlr4Grammar.py
boltun/engine/grammar/antlr4/Antlr4GrammarErrorStrategy.py
boltun/engine/grammar/antlr4/Antlr4GrammarLexer.py
boltun/engine/grammar/antlr4/Antlr4GrammarListener.py
boltun/engine/grammar/antlr4/Antlr4GrammarMode.py
boltun/engine/grammar/antlr4/Antlr4GrammarParser.py
boltun/engine/grammar/antlr4/Antlr4GrammarVisitor.py
boltun/engine/grammar/antlr4/__init__.py
boltun/engine/grammar/antlr4/node/__init__.py
boltun/engine/grammar/antlr4/node/fork/__init__.py
boltun/engine/grammar/antlr4/node/fork/_base.py
boltun/engine/grammar/antlr4/node/fork/choice.py
boltun/engine/grammar/antlr4/node/fork/content.py
boltun/engine/grammar/antlr4/node/fork/factory.py
boltun/engine/grammar/antlr4/node/fork/root.py
boltun/engine/grammar/antlr4/node/leaf/__init__.py
boltun/engine/grammar/antlr4/node/leaf/_base.py
boltun-0.6.0.dist-info/DESCRIPTION.rst
boltun-0.6.0.dist-info/METADATA
boltun-0.6.0.dist-info/RECORD
boltun-0.6.0.dist-info/WHEEL
boltun-0.6.0.dist-info/metadata.json
boltun-0.6.0.dist-info/top_level.txt
