Metadata-Version: 2.0
Name: boltun
Version: 0.6.0
Summary: Generate massive datasets from a single template file
Home-page: https://github.com/meiblorn/boltun
Author: Vadim Fedorenko (Meiblorn)
Author-email: meiblorn@gmail.com
License: MIT
Platform: UNKNOWN
Classifier: Development Status :: 4 - Beta
Classifier: License :: OSI Approved :: MIT License
Classifier: Topic :: Text Processing :: General
Classifier: Topic :: Text Processing :: Markup
Classifier: Topic :: Text Processing :: Linguistic
Classifier: Programming Language :: Python :: 3.5
Classifier: Programming Language :: Python :: 3.6
Classifier: Programming Language :: Python :: 3.7
Classifier: Intended Audience :: Developers
Classifier: Operating System :: OS Independent
Classifier: Topic :: Software Development :: Libraries :: Python Modules
Classifier: Topic :: Text Processing :: Markup
Requires-Python: >=3.5.*
Requires-Dist: antlr4-python3-runtime
Requires-Dist: attrs
Requires-Dist: PyYAML
Requires-Dist: six
Requires-Dist: path.py
Requires-Dist: enum34
